darbia/utils/__init__.py
darbia/utils/iterables.py
darbia/utils/mappings.py
darbia/utils/pandas_utils.py
darbia/utils/strings.py
darbiadev_utilities-0.7.0.dist-info/LICENSE
darbiadev_utilities-0.7.0.dist-info/METADATA
darbiadev_utilities-0.7.0.dist-info/WHEEL
darbiadev_utilities-0.7.0.dist-info/top_level.txt
darbiadev_utilities-0.7.0.dist-info/RECORD
