Metadata-Version: 2.1
Name: darbiadev-utilities
Version: 0.7.0
Summary: Namespace for utility functions
Author-email: Bradley Reynolds <bradley.reynolds@darbia.dev>
License: MIT
Project-URL: repository, https://github.com/darbiadev/darbiadev-utilities/
Project-URL: documentation, https://docs.darbia.dev/darbiadev-utilities/
Requires-Python: >=3.8
License-File: LICENSE
Provides-Extra: dev
Requires-Dist: pylint (>=2.12.2) ; extra == 'dev'
Requires-Dist: pytest (>=6.2.5) ; extra == 'dev'
Requires-Dist: pytest-cov (>=3.0.0) ; extra == 'dev'
Requires-Dist: black (>=21.12b0) ; extra == 'dev'
Requires-Dist: isort (>=5.10.1) ; extra == 'dev'
Provides-Extra: docs
Requires-Dist: sphinx (>=4.3.2) ; extra == 'docs'
Requires-Dist: sphinxcontrib-autoprogram (>=0.1.7) ; extra == 'docs'
Requires-Dist: sphinx-rtd-theme (>=1.0.0) ; extra == 'docs'
Requires-Dist: toml (>=0.10.2) ; extra == 'docs'
Provides-Extra: tests
Requires-Dist: pytest (>=6.2.5) ; extra == 'tests'
Requires-Dist: pandas ; extra == 'tests'
